mibig_taxa-0.1.4.dist-info/METADATA
mibig_taxa-0.1.4.dist-info/WHEEL
mibig_taxa-0.1.4.dist-info/license_files/LICENSE
mibig_taxa/__init__.py
mibig_taxa/mibig_taxa.cp38-win_amd64.pyd
mibig_taxa-0.1.4.dist-info/RECORD
