Metadata-Version: 2.1
Name: mibig-taxa
Version: 0.1.4
Classifier: Programming Language :: Rust
Classifier: Programming Language :: Python :: Implementation :: CPython
Classifier: Programming Language :: Python :: Implementation :: PyPy
License-File: LICENSE
Summary: Python bindings to the MIBiG taxon handling
License: Apache-2.0
Requires-Python: >=3.6
